Geo58/__init__.py
geo58-1.0.0b1.dist-info/LICENSE
geo58-1.0.0b1.dist-info/METADATA
geo58-1.0.0b1.dist-info/WHEEL
geo58-1.0.0b1.dist-info/top_level.txt
geo58-1.0.0b1.dist-info/RECORD
