Metadata-Version: 2.1
Name: geo58
Version: 1.0.0b1
Summary: Yet another short-link specification for geo-coordinates.
Home-page: https://github.com/flowolf/Geo58
Author: Florian Klien
Author-email: flowolf@klienux.org
License: UNKNOWN
Platform: UNKNOWN
Classifier: Programming Language :: Python :: 3
Classifier: License :: OSI Approved :: MIT License
Classifier: Operating System :: OS Independent
Classifier: Development Status :: 5 - Production/Stable
Classifier: Intended Audience :: Developers
Classifier: Topic :: Scientific/Engineering :: GIS
Requires-Python: >=3.6
